imgdataconvertcodegen/__init__.py
imgdataconvertcodegen/code_generator.py
imgdataconvertcodegen/end_metadata_mapper.py
imgdataconvertcodegen/image_data.py
imgdataconvertcodegen/interface_cmd.py
imgdataconvertcodegen/interface_py_api.py
imgdataconvertcodegen/metadata_differ.py
imgdataconvertcodegen/util.py
imgdataconvertcodegen/knowledge_graph_construction/ReadMe.md
imgdataconvertcodegen/knowledge_graph_construction/__init__.py
imgdataconvertcodegen/knowledge_graph_construction/constructor.py
imgdataconvertcodegen/knowledge_graph_construction/io.py
imgdataconvertcodegen/knowledge_graph_construction/knowledge_graph.json
imgdataconvertcodegen/knowledge_graph_construction/knowledge_graph.py
imgdataconvertcodegen/knowledge_graph_construction/sd.py
imgdataconvertcodegen/knowledge_graph_construction/edge_factories/PIL.py
imgdataconvertcodegen/knowledge_graph_construction/edge_factories/Pytorch.py
imgdataconvertcodegen/knowledge_graph_construction/edge_factories/ReadMe.md
imgdataconvertcodegen/knowledge_graph_construction/edge_factories/Tensorflow.py
imgdataconvertcodegen/knowledge_graph_construction/edge_factories/__init__.py
imgdataconvertcodegen/knowledge_graph_construction/edge_factories/inter_libs.py
imgdataconvertcodegen/knowledge_graph_construction/edge_factories/numpy.py
imgdataconvertcodegen/knowledge_graph_construction/edge_factories/type.py
imgdataconvertcodegen/knowledge_graph_construction/metedata/__init__.py
imgdataconvertcodegen/knowledge_graph_construction/metedata/type.py
imgdataconvertcodegen/knowledge_graph_construction/metedata/util.py
ImgDataConvertCodeGen-0.0.1.dist-info/LICENSE.txt
ImgDataConvertCodeGen-0.0.1.dist-info/METADATA
ImgDataConvertCodeGen-0.0.1.dist-info/WHEEL
ImgDataConvertCodeGen-0.0.1.dist-info/entry_points.txt
ImgDataConvertCodeGen-0.0.1.dist-info/top_level.txt
ImgDataConvertCodeGen-0.0.1.dist-info/RECORD
