Metadata-Version: 2.1
Name: ImgDataConvertCodeGen
Version: 0.0.1
Summary: Automatically generating conversion code for in-memory representations of images using a knowledge graph of data types.
Home-page: https://github.com/c3di/ImgDataConvertCodeGen
Author: Fei Chen
Author-email: boxchenfei@gmail.com
License: MIT
Project-URL: Source, https://github.com/c3di/ImgDataConvertCodeGen/
Project-URL: Tracker, https://github.com/c3di/ImgDataConvertCodeGen/issues
Platform: any
Classifier: Development Status :: 4 - Beta
Classifier: Programming Language :: Python
Requires-Python: <3.12,>=3.9
License-File: LICENSE.txt
Requires-Dist: importlib-metadata
Requires-Dist: networkx
Provides-Extra: testing
Requires-Dist: setuptools ; extra == 'testing'
Requires-Dist: pytest ; extra == 'testing'
Requires-Dist: pytest-cov ; extra == 'testing'
